AUTHORS
LICENSE
README.creole
django_processinfo/__init__.py
django_processinfo/admin.py
django_processinfo/app_settings.py
django_processinfo/apps.py
django_processinfo/middlewares.py
django_processinfo/migrations/0001_initial.py
django_processinfo/migrations/0002_auto_20180309_1608.py
django_processinfo/migrations/0003_auto_20201102_0844.py
django_processinfo/migrations/0004_auto_20201209_1313.py
django_processinfo/migrations/__init__.py
django_processinfo/models.py
django_processinfo/publish.py
django_processinfo/templates/admin/django_processinfo/change_form.html
django_processinfo/templates/admin/django_processinfo/change_list.html
django_processinfo/templates/django_processinfo/includes/admin_breadcrumbs.html
django_processinfo/templates/django_processinfo/timesince.html
django_processinfo/utils/__init__.py
django_processinfo/utils/average.py
django_processinfo/utils/human_time.py
django_processinfo/utils/proc_info.py
django_processinfo-1.1.0.dist-info/entry_points.txt
django_processinfo-1.1.0.dist-info/LICENSE
django_processinfo-1.1.0.dist-info/WHEEL
django_processinfo-1.1.0.dist-info/METADATA
django_processinfo-1.1.0.dist-info/RECORD
