Metadata-Version: 2.1
Name: django-processinfo
Version: 1.1.0
Summary: Django application to collect information about the running server processes.
License: GNU General Public License v3.0 or above
Keywords: django
Author: JensDiemer
Author-email: git@jensdiemer.de
Requires-Python: >=3.7,<4.0.0
Classifier: License :: Other/Proprietary License
Classifier: Programming Language :: Python :: 3
Classifier: Programming Language :: Python :: 3.10
Classifier: Programming Language :: Python :: 3.7
Classifier: Programming Language :: Python :: 3.8
Classifier: Programming Language :: Python :: 3.9
Requires-Dist: Django
